<?xml version='1.0' encoding='UTF-8'?>
<annotation>
  <folder>output</folder>
  <filename>comprimidos-na-mao-da-mulher_93675-5612.jpg</filename>
  <path>c:\Users\Msi\Documents\S6\S6_Projets\XML\Pill_Project\pillsPicture\images\comprimidos-na-mao-da-mulher_93675-5612.jpg</path>
  <size>
    <width>626</width>
    <height>417</height>
    <depth>3</depth>
  </size>
  <segmented>0</segmented>
  <object>
    <name>round_white</name>
    <shape>round</shape>
    <color>white</color>
    <pose>Unspecified</pose>
    <truncated>0</truncated>
    <difficult>0</difficult>
    <bndbox>
      <xmin>242</xmin>
      <ymin>120</ymin>
      <xmax>366</xmax>
      <ymax>241</ymax>
    </bndbox>
  </object>
  <object>
    <name>round_white</name>
    <shape>round</shape>
    <color>white</color>
    <pose>Unspecified</pose>
    <truncated>0</truncated>
    <difficult>0</difficult>
    <bndbox>
      <xmin>335</xmin>
      <ymin>215</ymin>
      <xmax>417</xmax>
      <ymax>291</ymax>
    </bndbox>
  </object>
</annotation>
