<?xml version='1.0' encoding='UTF-8'?>
<annotation>
  <folder>output</folder>
  <filename>medicine(17).jpg</filename>
  <path>c:\Users\Msi\Documents\S6\S6_Projets\XML\Pill_Project\pillsPicture\images\medicine(17).jpg</path>
  <size>
    <width>2448</width>
    <height>3264</height>
    <depth>3</depth>
  </size>
  <segmented>0</segmented>
  <object>
    <name>oval_red</name>
    <shape>oval</shape>
    <color>red</color>
    <pose>Unspecified</pose>
    <truncated>0</truncated>
    <difficult>0</difficult>
    <bndbox>
      <xmin>297</xmin>
      <ymin>1259</ymin>
      <xmax>725</xmax>
      <ymax>1690</ymax>
    </bndbox>
  </object>
  <object>
    <name>round_white</name>
    <shape>round</shape>
    <color>white</color>
    <pose>Unspecified</pose>
    <truncated>0</truncated>
    <difficult>0</difficult>
    <bndbox>
      <xmin>1166</xmin>
      <ymin>1510</ymin>
      <xmax>1577</xmax>
      <ymax>1890</ymax>
    </bndbox>
  </object>
  <object>
    <name>round_white</name>
    <shape>round</shape>
    <color>white</color>
    <pose>Unspecified</pose>
    <truncated>0</truncated>
    <difficult>0</difficult>
    <bndbox>
      <xmin>1277</xmin>
      <ymin>1769</ymin>
      <xmax>1701</xmax>
      <ymax>2131</ymax>
    </bndbox>
  </object>
  <object>
    <name>round_white</name>
    <shape>round</shape>
    <color>white</color>
    <pose>Unspecified</pose>
    <truncated>0</truncated>
    <difficult>0</difficult>
    <bndbox>
      <xmin>1270</xmin>
      <ymin>2121</ymin>
      <xmax>1718</xmax>
      <ymax>2593</ymax>
    </bndbox>
  </object>
  <object>
    <name>oval_red</name>
    <shape>oval</shape>
    <color>red</color>
    <pose>Unspecified</pose>
    <truncated>0</truncated>
    <difficult>0</difficult>
    <bndbox>
      <xmin>518</xmin>
      <ymin>2310</ymin>
      <xmax>991</xmax>
      <ymax>2724</ymax>
    </bndbox>
  </object>
  <object>
    <name>round_gray</name>
    <shape>round</shape>
    <color>gray</color>
    <pose>Unspecified</pose>
    <truncated>0</truncated>
    <difficult>0</difficult>
    <bndbox>
      <xmin>825</xmin>
      <ymin>2007</ymin>
      <xmax>1273</xmax>
      <ymax>2483</ymax>
    </bndbox>
  </object>
  <object>
    <name>oval_gray</name>
    <shape>oval</shape>
    <color>gray</color>
    <pose>Unspecified</pose>
    <truncated>0</truncated>
    <difficult>0</difficult>
    <bndbox>
      <xmin>425</xmin>
      <ymin>2086</ymin>
      <xmax>839</xmax>
      <ymax>2373</ymax>
    </bndbox>
  </object>
  <object>
    <name>round_white</name>
    <shape>round</shape>
    <color>white</color>
    <pose>Unspecified</pose>
    <truncated>0</truncated>
    <difficult>0</difficult>
    <bndbox>
      <xmin>756</xmin>
      <ymin>1710</ymin>
      <xmax>1163</xmax>
      <ymax>2124</ymax>
    </bndbox>
  </object>
  <object>
    <name>round_gray</name>
    <shape>round</shape>
    <color>gray</color>
    <pose>Unspecified</pose>
    <truncated>0</truncated>
    <difficult>0</difficult>
    <bndbox>
      <xmin>473</xmin>
      <ymin>1642</ymin>
      <xmax>901</xmax>
      <ymax>2069</ymax>
    </bndbox>
  </object>
</annotation>
